[
  {
    "inputs": [
      {
        "internalType": "address",
        "name": "_campaignAddress",
        "type": "address"
      }
    ],
    "name": "CrowdFunder__CampaignStillActive",
    "type": "error"
  },
  {
    "inputs": [
      {
        "internalType": "address",
        "name": "_campaignAddress",
        "type": "address"
      }
    ],
    "name": "CrowdFunder__DonationFailed",
    "type": "error"
  },
  {
    "inputs": [
      { "internalType": "address", "name": "_caller", "type": "address" },
      {
        "internalType": "address",
        "name": "_campaignAddress",
        "type": "address"
      }
    ],
    "name": "CrowdFunder__NotCreator",
    "type": "error"
  },
  {
    "inputs": [
      {
        "internalType": "address",
        "name": "_campaignAddress",
        "type": "address"
      }
    ],
    "name": "CrowdFunder__RefundFailed",
    "type": "error"
  },
  {
    "anonymous": false,
    "inputs": [
      {
        "indexed": true,
        "internalType": "address",
        "name": "_campaignAddress",
        "type": "address"
      },
      {
        "indexed": true,
        "internalType": "address",
        "name": "_creator",
        "type": "address"
      },
      {
        "indexed": false,
        "internalType": "string",
        "name": "_category",
        "type": "string"
      },
      {
        "indexed": false,
        "internalType": "string[]",
        "name": "_tags",
        "type": "string[]"
      }
    ],
    "name": "miiCampaignAdded",
    "type": "event"
  },
  {
    "anonymous": false,
    "inputs": [
      {
        "indexed": true,
        "internalType": "address",
        "name": "_funder",
        "type": "address"
      },
      {
        "indexed": true,
        "internalType": "address",
        "name": "_campaignAddress",
        "type": "address"
      }
    ],
    "name": "miiCampaignFunded",
    "type": "event"
  },
  {
    "anonymous": false,
    "inputs": [
      {
        "indexed": true,
        "internalType": "address",
        "name": "_campaignAddress",
        "type": "address"
      }
    ],
    "name": "miiCampaignRemoved",
    "type": "event"
  },
  {
    "anonymous": false,
    "inputs": [
      {
        "indexed": true,
        "internalType": "address",
        "name": "_withdrawer",
        "type": "address"
      },
      {
        "indexed": true,
        "internalType": "address",
        "name": "_campaignAddress",
        "type": "address"
      }
    ],
    "name": "miiCampaignShrunk",
    "type": "event"
  },
  {
    "anonymous": false,
    "inputs": [
      {
        "indexed": true,
        "internalType": "address",
        "name": "_address",
        "type": "address"
      },
      {
        "indexed": false,
        "internalType": "string",
        "name": "_username",
        "type": "string"
      },
      {
        "indexed": false,
        "internalType": "string",
        "name": "_twitter",
        "type": "string"
      },
      {
        "indexed": false,
        "internalType": "string",
        "name": "_email",
        "type": "string"
      },
      {
        "indexed": false,
        "internalType": "string",
        "name": "_sig",
        "type": "string"
      }
    ],
    "name": "miiUserAdded",
    "type": "event"
  },
  {
    "anonymous": false,
    "inputs": [
      {
        "indexed": false,
        "internalType": "address",
        "name": "_userAddress",
        "type": "address"
      },
      {
        "indexed": false,
        "internalType": "string",
        "name": "_homeAddr",
        "type": "string"
      }
    ],
    "name": "miiUserHomeAddrAdded",
    "type": "event"
  },
  {
    "inputs": [
      { "internalType": "string", "name": "_title", "type": "string" },
      { "internalType": "string", "name": "_description", "type": "string" },
      { "internalType": "string", "name": "_category", "type": "string" },
      { "internalType": "string[]", "name": "_tags", "type": "string[]" },
      { "internalType": "uint256", "name": "_goalAmount", "type": "uint256" },
      { "internalType": "uint256", "name": "_duration", "type": "uint256" },
      { "internalType": "string", "name": "_imageURI", "type": "string" }
    ],
    "name": "addCampaign",
    "outputs": [],
    "stateMutability": "nonpayable",
    "type": "function"
  },
  {
    "inputs": [
      { "internalType": "address", "name": "_address", "type": "address" },
      { "internalType": "string", "name": "_username", "type": "string" },
      { "internalType": "string", "name": "_twitter", "type": "string" },
      { "internalType": "string", "name": "_email", "type": "string" },
      { "internalType": "string", "name": "_sig", "type": "string" }
    ],
    "name": "addUser",
    "outputs": [],
    "stateMutability": "nonpayable",
    "type": "function"
  },
  {
    "inputs": [
      { "internalType": "address", "name": "_userAddress", "type": "address" },
      { "internalType": "string", "name": "_homeAddr", "type": "string" }
    ],
    "name": "addUserHomeAddr",
    "outputs": [],
    "stateMutability": "nonpayable",
    "type": "function"
  },
  {
    "inputs": [],
    "name": "campaignCounter",
    "outputs": [{ "internalType": "uint256", "name": "", "type": "uint256" }],
    "stateMutability": "view",
    "type": "function"
  },
  {
    "inputs": [
      {
        "internalType": "address",
        "name": "_campaignAddress",
        "type": "address"
      }
    ],
    "name": "donateToCampaign",
    "outputs": [],
    "stateMutability": "payable",
    "type": "function"
  },
  {
    "inputs": [
      {
        "internalType": "address",
        "name": "_campaignAddress",
        "type": "address"
      },
      { "internalType": "address", "name": "_donator", "type": "address" }
    ],
    "name": "refundFromCampaign",
    "outputs": [],
    "stateMutability": "nonpayable",
    "type": "function"
  },
  {
    "inputs": [
      {
        "internalType": "address",
        "name": "_campaignAddress",
        "type": "address"
      }
    ],
    "name": "removeCampaign",
    "outputs": [],
    "stateMutability": "nonpayable",
    "type": "function"
  }
]
